README.md
setup.py
tweb/__init__.py
tweb/access_token.py
tweb/application.py
tweb/base_handler.py
tweb/code.py
tweb/dbpool.py
tweb/error_exception.py
tweb/json_util.py
tweb/license.py
tweb/myweb.py
tweb/rdpool.py
tweb/scheduler.py
tweb/snowflake.py
tweb/time.py
tweb/tools.py
tweb/url.py
tweb/aliyunsdkdysmsapi/__init__.py
tweb/aliyunsdkdysmsapi/request/__init__.py
tweb/aliyunsdkdysmsapi/request/v20170525/QueryInterSmsIsoInfoRequest.py
tweb/aliyunsdkdysmsapi/request/v20170525/QuerySendDetailsRequest.py
tweb/aliyunsdkdysmsapi/request/v20170525/QueryTokenForMnsQueueRequest.py
tweb/aliyunsdkdysmsapi/request/v20170525/SendBatchSmsRequest.py
tweb/aliyunsdkdysmsapi/request/v20170525/SendInterSmsRequest.py
tweb/aliyunsdkdysmsapi/request/v20170525/SendSmsRequest.py
tweb/aliyunsdkdysmsapi/request/v20170525/__init__.py
tweb/mq/__init__.py
tweb/mq/receiver.py
tweb/mq/sender.py
tweb_sdk.egg-info/PKG-INFO
tweb_sdk.egg-info/SOURCES.txt
tweb_sdk.egg-info/dependency_links.txt
tweb_sdk.egg-info/requires.txt
tweb_sdk.egg-info/top_level.txt