Metadata-Version: 1.2
Name: tweb-sdk
Version: 0.1.12
Summary: Web server framework based on tornado
Home-page: https://gitee.com/qcc100/tweb-sdk.git
Author: Yang Chunbo
Author-email: ycb@microto.com
Maintainer: Yang Chunbo
Maintainer-email: ycb@microto.com
License: MIT License
Platform: all
Classifier: Development Status :: 4 - Beta
Classifier: Operating System :: OS Independent
Classifier: Intended Audience :: Developers
Classifier: License :: OSI Approved :: MIT License
Classifier: Programming Language :: Python
Classifier: Programming Language :: Python :: Implementation
Classifier: Programming Language :: Python :: 3
Classifier: Programming Language :: Python :: 3.4
Classifier: Programming Language :: Python :: 3.5
Classifier: Programming Language :: Python :: 3.6
Classifier: Topic :: Software Development :: Libraries
